README.md
setup.py
geneview/__init__.py
geneview/conftest.py
geneview.egg-info/PKG-INFO
geneview.egg-info/SOURCES.txt
geneview.egg-info/dependency_links.txt
geneview.egg-info/requires.txt
geneview.egg-info/top_level.txt
geneview/algorithm/__init__.py
geneview/algorithm/_cluster.py
geneview/baseplot/__init__.py
geneview/baseplot/_forest.py
geneview/baseplot/_venn.py
geneview/genome_tracks/__init__.py
geneview/gwas/__init__.py
geneview/gwas/_locuszoom.py
geneview/gwas/_manhattan.py
geneview/gwas/_qq.py
geneview/karyotype/__init__.py
geneview/karyotype/_karyotype.py
geneview/palette/__init__.py
geneview/palette/_circos.py
geneview/palette/_palettes.py
geneview/palette/_xkcd_rgb.py
geneview/popgene/__init__.py
geneview/popgene/_admixture.py
geneview/popgene/_ldblock.py
geneview/tests/__init__.py
geneview/tests/test_algorithms.py
geneview/tests/test_decorators.py
geneview/utils/__init__.py
geneview/utils/_adjust_text.py
geneview/utils/_dataset.py
geneview/utils/_decorators.py
geneview/utils/_misc.py