Metadata-Version: 2.1
Name: geneview
Version: 0.1.3
Summary: Geneview: A python package for genomics data visualization.
Home-page: https://github.com/ShujiaHuang/geneview
Author: Shujia Huang
Author-email: huangshujia9@gmail.com
Maintainer: Shujia Huang
Maintainer-email: huangshujia9@gmail.com
License: BSD (3-clause)
Download-URL: https://github.com/ShujiaHuang/geneview
Platform: UNKNOWN
Classifier: Intended Audience :: Science/Research
Classifier: Programming Language :: Python :: 3.7
Classifier: Programming Language :: Python :: 3.8
Classifier: Programming Language :: Python :: 3.9
Classifier: License :: OSI Approved :: BSD License
Classifier: Topic :: Scientific/Engineering :: Bio-Informatics
Classifier: Topic :: Scientific/Engineering :: Visualization
Classifier: Topic :: Multimedia :: Graphics
Classifier: Operating System :: POSIX
Classifier: Operating System :: Unix
Classifier: Operating System :: MacOS
